pydnp3.cpython-310-x86_64-linux-gnu.so
dnp3_python/__init__.py
dnp3_python/py.typed
dnp3_python/dnp3station/__init__.py
dnp3_python/dnp3station/master.py
dnp3_python/dnp3station/outstation.py
dnp3_python/dnp3station/station_utils.py
dnp3_python/dnp3station/visitors.py
dnp3demo/__main__.py
dnp3demo/control_workflow_demo.py
dnp3demo/data_retrieval_demo.py
dnp3demo/multi_stations_demo.py
dnp3demo/run_master.py
dnp3demo/run_outstation.py
opendnp3_nightly-0.3.0.dist-info/LICENSE
opendnp3_nightly-0.3.0.dist-info/METADATA
opendnp3_nightly-0.3.0.dist-info/WHEEL
opendnp3_nightly-0.3.0.dist-info/entry_points.txt
opendnp3_nightly-0.3.0.dist-info/top_level.txt
opendnp3_nightly-0.3.0.dist-info/RECORD
