Metadata-Version: 2.1
Name: opendnp3-nightly
Version: 0.3.0
Summary: pydnp3 -- python binding for opendnp3
Home-page: https://github.com/kefeimo/dnp3-python
Author: Volttron Team
Author-email: volttron@pnnl.gov
License-File: LICENSE
